{
  "Package": {
    "Name": "Smart Building Demo Starter",
    "Description": "A starter for custom smart buildings apps that utilizes IoT and Weather data.",
    "Button": "Launch Smart Building",
    "Image": "https://www.fathym.com/dashboard/assets/images/black_thinky.png",
    "PreviewImage": "https://www.fathym.com/dashboard/assets/images/black_thinky.png",
    "SourceCode": "https://github.com/fathym-it/smart-building-demo",
    "SuccessType": "Project"
  },
  "EaC": "./assets/eac.json",
  "Parameters": "./assets/parameters.json"
}
